{"data":{"site":{"siteMetadata":{"siteUrl":"http://ghost.local:8000","title":"vwa.la help","description":"Everything you need to know about the vwa.la influencer marketing platform."}},"markdownRemark":{"frontmatter":{"title":"Is referral, affiliate and influencer marketing the same thing?","date":null,"date_pretty":null,"path":null,"meta_title":"Referral, affiliate and influencer marketing refers to the same thing","meta_description":"","image":null,"next":null,"sidebar":"merchant","toc":null,"keywords":["merchant","help"]},"html":"<p>Yep, that's right. </p>\n<p>Referral/affiliate/influencer marketing bascially mean the same thing. There are subtle differences, but they are trivial in practice. So feel free to use whichever term suits your brand the best!</p>","fields":{"slug":"/merchant/is-referral-affiliate-influencer-marketing-the-same-thing/"},"timeToRead":1,"excerpt":"Yep, that's right.  Referral/affiliate/influencer marketing bascially mean the same thing. There are subtle differences, but they are…"}},"pageContext":{"slug":"/merchant/is-referral-affiliate-influencer-marketing-the-same-thing/"}}